non_uniform_piecewise_layers/__init__.py
non_uniform_piecewise_layers/adaptive_piecewise_conv.py
non_uniform_piecewise_layers/adaptive_piecewise_linear.py
non_uniform_piecewise_layers/adaptive_piecewise_mingru.py
non_uniform_piecewise_layers/adaptive_piecewise_mlp.py
non_uniform_piecewise_layers/custom_positions_conv.py
non_uniform_piecewise_layers/efficient_adaptive_piecewise_conv.py
non_uniform_piecewise_layers/fast_triton_adaptive_piecewise_conv.py
non_uniform_piecewise_layers/hybrid_triton_adaptive_piecewise_conv.py
non_uniform_piecewise_layers/oja_backprop.py
non_uniform_piecewise_layers/optimized_triton_adaptive_piecewise_conv.py
non_uniform_piecewise_layers/piecewise_linear.py
non_uniform_piecewise_layers/rotation_layer.py
non_uniform_piecewise_layers/test_piecewise.py
non_uniform_piecewise_layers/triton_adaptive_piecewise_conv.py
non_uniform_piecewise_layers/utils.py
non_uniform_piecewise_layers/visualization.py
non_uniform_piecewise_layers-0.3.0.dist-info/METADATA
non_uniform_piecewise_layers-0.3.0.dist-info/WHEEL
non_uniform_piecewise_layers-0.3.0.dist-info/licenses/LICENSE
non_uniform_piecewise_layers-0.3.0.dist-info/RECORD
