Metadata-Version: 2.4
Name: non-uniform-piecewise-layers
Version: 0.3.0
Author-email: jloveric <john.loverich@gmail.com>
License-Expression: MIT
License-File: LICENSE
Requires-Python: ~=3.10
Requires-Dist: click<9,>=8.1.8
Requires-Dist: lion-pytorch<0.3,>=0.2.3
Requires-Dist: numpy<3,>=2.2.2
Requires-Dist: torch>=2.9.1
Requires-Dist: torchvision>=0.24.1
Requires-Dist: tqdm<5,>=4.67.1
Requires-Dist: triton<4,>=3.2.0
